{
  "project_info": {
    "project_number": "44950152191",
    "project_id": "udharoo-staging",
    "storage_bucket": "udharoo-staging.firebasestorage.app"
  },
  "client": [
    {
      "client_info": {
        "mobilesdk_app_id": "1:44950152191:android:c77fbb8b21623a856ebdca",
        "android_client_info": {
          "package_name": "com.udharoo.staging"
        }
      },
      "oauth_client": [
        {
          "client_id": "44950152191-kcdq760hfoqk6f8dsaohcnv1rj421ibe.apps.googleusercontent.com",
          "client_type": 1,
          "android_info": {
            "package_name": "com.udharoo.staging",
            "certificate_hash": "82e08ceac2da9c9fb6135404d819c8dff07be24d"
          }
        },
        {
          "client_id": "44950152191-r5bmocc8kcvaqt3os498tpcqgm9l6d8b.apps.googleusercontent.com",
          "client_type": 1,
          "android_info": {
            "package_name": "com.udharoo.staging",
            "certificate_hash": "d084151358ff3b1dcb1fe5f586bd7d837d4b84f8"
          }
        },
        {
          "client_id": "44950152191-2vel0rdm2g19tbes0ip9uktheenujf2i.apps.googleusercontent.com",
          "client_type": 3
        }
      ],
      "api_key": [
        {
          "current_key": "AIzaSyAlZJTn3oHPJASpWBaRozbG6GZkwjb0XcM"
        }
      ],
      "services": {
        "appinvite_service": {
          "other_platform_oauth_client": [
            {
              "client_id": "44950152191-2vel0rdm2g19tbes0ip9uktheenujf2i.apps.googleusercontent.com",
              "client_type": 3
            },
            {
              "client_id": "44950152191-sdsjanc2it4hivjcb7c2md7gu8pm7ob2.apps.googleusercontent.com",
              "client_type": 2,
              "ios_info": {
                "bundle_id": "com.example.udharoo"
              }
            }
          ]
        }
      }
    }
  ],
  "configuration_version": "1"
}